{
  "version": "53.0",
  "base": "v51 stable app structure; v52 mobile gesture queue removed",
  "checks": {
    "javascript_syntax_ok": true,
    "version_badge_v53": true,
    "cache_busting_v53": true,
    "initiative_only_once": true,
    "full_v4_voice_engine": true,
    "direct_speech_synthesis": true,
    "v52_gesture_queue_removed": true,
    "playback_chain_restored": true,
    "online_tts_removed": true,
    "local_sprite_removed": true,
    "service_worker_not_registered": true
  },
  "node_check_stderr": "",
  "initiative_count": 1,
  "notes": [
    "This repairs the card flip/playback regression by returning to v51 structure.",
    "Dari remains browser-only fa-AF direct SpeechSynthesis.",
    "If Dari still fails on mobile, it is independent of the flip/playback bug."
  ],
  "zip_mb": 0.18
}